hdaf_filter/__init__.py
hdaf_filter/__main__.py
hdaf_filter/hdaf.py
hdaf_filter/input_output.py
hdaf_filter/util.py
hdaf_filter-0.1.1.dist-info/METADATA
hdaf_filter-0.1.1.dist-info/WHEEL
hdaf_filter-0.1.1.dist-info/top_level.txt
hdaf_filter-0.1.1.dist-info/RECORD
