Metadata-Version: 2.1
Name: hdaf-filter
Version: 0.1.1
Summary: Fourier filtering using the Hermite Distributed Approximation Functions as the low-pass filter
Home-page: https://github.com/paul-hernandez-herrera/hdaf_filtering
Author: Paúl Hernández-Herrera
Author-email: paul.hernandez@ibt.unam.mx
License: BSD 3-clause
Platform: UNKNOWN
Classifier: Intended Audience :: Science/Research
Classifier: License :: OSI Approved :: BSD License
Classifier: Operating System :: OS Independent
Classifier: Programming Language :: Python :: 3.8
Requires-Dist: matplotlib (>=3.2.2)
Requires-Dist: numpy (>=1.21.6)
Requires-Dist: setuptools (>=57.4.0)
Requires-Dist: tifffile (>=2021.11.2)
